Metadata-Version: 2.1
Name: tatik-calc
Version: 1.0
Summary: Калькулятор
Author: Natali
Author-email: tatiksunny1@gmail.com
